LICENSE
MANIFEST.in
README.md
btoon_python.cpp
pyproject.toml
setup.py
test_comprehensive.py
test_quick.py
btoon/__init__.py
btoon/__init__.pyi
btoon/py.typed
btoon.egg-info/PKG-INFO
btoon.egg-info/SOURCES.txt
btoon.egg-info/dependency_links.txt
btoon.egg-info/not-zip-safe
btoon.egg-info/requires.txt
btoon.egg-info/top_level.txt
core/CMakeLists.txt
core/LICENSE
core/README.md
core/include/btoon/batch_processor.h
core/include/btoon/btoon.h
core/include/btoon/capi.h
core/include/btoon/compression.h
core/include/btoon/decimal.h
core/include/btoon/decoder.h
core/include/btoon/delta_codec.h
core/include/btoon/dictionary_codec.h
core/include/btoon/encoder.h
core/include/btoon/graph.h
core/include/btoon/graphql_schema.h
core/include/btoon/json_schema.h
core/include/btoon/memory_pool.h
core/include/btoon/rle_codec.h
core/include/btoon/schema.h
core/include/btoon/security.h
core/include/btoon/stream_decoder.h
core/include/btoon/stream_encoder.h
core/include/btoon/timeseries.h
core/include/btoon/utils.h
core/include/btoon/validator.h
core/include/btoon/zero_copy.h
core/include/third_party/nlohmann/json.hpp
core/src/btoon.cpp
core/src/capi.cpp
core/src/compression.cpp
core/src/decoder.cpp
core/src/delta_codec.cpp
core/src/dictionary_codec.cpp
core/src/encoder.cpp
core/src/memory_pool.cpp
core/src/rle_codec.cpp
core/src/schema.cpp
core/src/security.cpp
core/src/stream_decoder.cpp
core/src/stream_encoder.cpp
core/src/validator.cpp
core/src/zero_copy.cpp
examples/01_basic.py
examples/02_compression.py