Metadata-Version: 2.4
Name: btoon
Version: 0.0.1
Summary: High-performance binary serialization format for Python
Home-page: https://github.com/BTOON-project/btoon-python
Author: BTOON Contributors
Author-email: BTOON Contributors <hello@btoon.net>
License: MIT
Project-URL: Homepage, https://btoon.net
Project-URL: Documentation, https://btoon.net/docs
Project-URL: Repository, https://github.com/BTOON-project/btoon-python
Project-URL: Issues, https://github.com/BTOON-project/btoon-python/issues
Keywords: serialization,binary,messagepack,compression,performance,tabular,data
Classifier: Development Status :: 4 - Beta
Classifier: Intended Audience :: Developers
Classifier: Programming Language :: Python :: 3
Classifier: Programming Language :: Python :: 3.8
Classifier: Programming Language :: Python :: 3.9
Classifier: Programming Language :: Python :: 3.10
Classifier: Programming Language :: Python :: 3.11
Classifier: Programming Language :: Python :: 3.12
Classifier: Programming Language :: Python :: Implementation :: CPython
Classifier: Programming Language :: C++
Classifier: Topic :: Software Development :: Libraries :: Python Modules
Classifier: Topic :: System :: Archiving :: Compression
Classifier: Topic :: Internet :: WWW/HTTP :: Dynamic Content
Classifier: Topic :: Database
Classifier: Topic :: Scientific/Engineering
Classifier: Operating System :: OS Independent
Classifier: Operating System :: POSIX :: Linux
Classifier: Operating System :: MacOS :: MacOS X
Classifier: Operating System :: Microsoft :: Windows
Requires-Python: >=3.7
License-File: LICENSE
Provides-Extra: dev
Requires-Dist: pytest>=7.0; extra == "dev"
Requires-Dist: pytest-cov; extra == "dev"
Requires-Dist: pytest-benchmark; extra == "dev"
Requires-Dist: black; extra == "dev"
Requires-Dist: flake8; extra == "dev"
Requires-Dist: mypy; extra == "dev"
Requires-Dist: build; extra == "dev"
Requires-Dist: twine; extra == "dev"
Provides-Extra: numpy
Requires-Dist: numpy>=1.19.0; extra == "numpy"
Provides-Extra: pandas
Requires-Dist: pandas>=1.2.0; extra == "pandas"
Requires-Dist: numpy>=1.19.0; extra == "pandas"
Provides-Extra: full
Requires-Dist: numpy>=1.19.0; extra == "full"
Requires-Dist: pandas>=1.2.0; extra == "full"
Requires-Dist: aiofiles>=0.8.0; extra == "full"
Dynamic: author
Dynamic: home-page
Dynamic: license-file
Dynamic: requires-python
